HuggingSimpleCuellar_lib/__init__.py
huggingsimplecuellar_lib-1.0.2.dist-info/METADATA
huggingsimplecuellar_lib-1.0.2.dist-info/WHEEL
huggingsimplecuellar_lib-1.0.2.dist-info/licenses/LICENSE
huggingsimplecuellar_lib-1.0.2.dist-info/RECORD
