Metadata-Version: 2.1
Name: HuggingSimpleCuellar_lib
Version: 1.0.2
Summary: Una libreria simple para usar modelos de Huggingface
Project-URL: Homepage, https://github.com/pypa/sampleproject
Project-URL: Bug Tracker, https://github.com/pypa/sampleproject/issues
Author-email: Emiliano Cuellar <ec446162@gmail.com>
License-File: LICENSE
Classifier: License :: OSI Approved :: MIT License
Classifier: Operating System :: OS Independent
Classifier: Programming Language :: Python :: 3
Requires-Python: >=3.7
Requires-Dist: accelerate
Requires-Dist: diffusers
Requires-Dist: pillow
Requires-Dist: requests
Requires-Dist: tensorflow
Requires-Dist: torch
Requires-Dist: transformers
